README.rst
coop/__init__.py
coop/blocks.py
coop/forms.py
coop/logging.py
coop/models.py
coop/page.py
coop/settings.py
coop/test.py
coop/urls.py
coop/vite_client.py
coop/wagtail_hooks.py
coop/wsgi.py
coop/wsgi_dev.py
coop/factories/__init__.py
coop/factories/attributes.py
coop/factories/blocks.py
coop/factories/fuzzy.py
coop/factories/inline.py
coop/form_builder/__init__.py
coop/form_builder/blocks.py
coop/form_builder/factories.py
coop/form_builder/forms.py
coop/form_builder/page.py
coop/form_builder/views.py
coop/jinja2/coop/analytics_warning.html
coop/jinja2tags/__init__.py
coop/jinja2tags/core.py
coop/jinja2tags/vite.py
coop/jinja2tags/webpack.py
coop/migrations/0001_remove_site.py
coop/migrations/0002_analyticssettings.py
coop/migrations/0003_tag_manager_settings.py
coop/migrations/0004_increase_analytics_length.py
coop/migrations/__init__.py
coop/styleguide/__init__.py
coop/styleguide/urls.py
coop/styleguide/views.py
coop/users/__init__.py
coop/users/models.py
coop/utils/__init__.py
coop/utils/forms.py
coop/utils/mailchimp.py
coop/utils/migrations.py
coop/utils/pagination.py
coop/utils/rich_text_example.html
coop/utils/testdata.py
coop/utils/views.py
coop/utils/test_documents/magazine-article.pdf
coop/utils/test_documents/nj-logos.pdf
coop/utils/test_images/landscape-large.jpg
coop/utils/test_images/landscape-small.jpeg
coop/utils/test_images/portrait-large.jpg
coop/utils/test_images/portrait-small.jpeg
coop-7.2.0.dist-info/METADATA
coop-7.2.0.dist-info/WHEEL
coop-7.2.0.dist-info/RECORD
