Metadata-Version: 2.4
Name: coop
Version: 7.2.0
Summary: Standard base to build Wagtail sites from
Author-email: Neon Jungle <developers@neonjungle.studio>
Requires-Python: <4.0,>=3.10
Requires-Dist: django-htmx<1.27.0,>=1.26.0
Requires-Dist: django<5.3,>=4.2
Requires-Dist: jinja2>=3.1.0
Requires-Dist: psycopg[binary]<4.0.0,>=3.2.6
Requires-Dist: pytz
Requires-Dist: sentry-sdk[django]>=2.13.0
Requires-Dist: wagtail-cache<3.1.0,>=3.0.0
Requires-Dist: wagtail-factories~=4.3.0
Requires-Dist: wagtail-icomoon
Requires-Dist: wagtail-metadata==5.0.0
Requires-Dist: wagtail<7.3.0,>=7.2.0
Provides-Extra: cache
Requires-Dist: diskcache~=5.2.0; extra == 'cache'
Provides-Extra: mailchimp
Requires-Dist: mailchimp3~=3.0.0; extra == 'mailchimp'
Provides-Extra: s3
Requires-Dist: collectfasta<4.0.0,>=3.2.1; extra == 's3'
Requires-Dist: django-storages[s3]~=1.14.0; extra == 's3'
Provides-Extra: vite
Requires-Dist: django-vite<3.2.0,>=3.0.0; extra == 'vite'
Provides-Extra: webpack
Requires-Dist: django-webpack-loader~=1.8.0; extra == 'webpack'
